fastybird_redisdb_storage_plugin/__init__.py
fastybird_redisdb_storage_plugin/bootstrap.py
fastybird_redisdb_storage_plugin/connection.py
fastybird_redisdb_storage_plugin/exceptions.py
fastybird_redisdb_storage_plugin/logger.py
fastybird_redisdb_storage_plugin/manager.py
fastybird_redisdb_storage_plugin/py.typed
fastybird_redisdb_storage_plugin/repository.py
fastybird_redisdb_storage_plugin/state.py
tests/__init__.py
tests/pytests/__init__.py
tests/pytests/tests.py
fastybird_redisdb_storage_plugin-0.10.0.dist-info/LICENSE.md
fastybird_redisdb_storage_plugin-0.10.0.dist-info/METADATA
fastybird_redisdb_storage_plugin-0.10.0.dist-info/WHEEL
fastybird_redisdb_storage_plugin-0.10.0.dist-info/top_level.txt
fastybird_redisdb_storage_plugin-0.10.0.dist-info/RECORD
